{"metadata": {"dbt_schema_version": "https://schemas.getdbt.com/dbt/run-results/v6.json", "dbt_version": "1.9.3", "generated_at": "2025-04-08T10:05:32.250972Z", "invocation_id": "9280a4d3-021c-4678-8d89-55cba31cd400", "env": {}}, "results": [{"status": "success", "timing": [{"name": "compile", "started_at": "2025-04-08T10:05:31.111657Z", "completed_at": "2025-04-08T10:05:31.130482Z"}, {"name": "execute", "started_at": "2025-04-08T10:05:31.131962Z", "completed_at": "2025-04-08T10:05:31.388820Z"}], "thread_id": "Thread-1", "execution_time": 0.2808494567871094, "adapter_response": {"_message": "SELECT 7775", "code": "SELECT", "rows_affected": 7775}, "message": "SELECT 7775", "failures": null, "unique_id": "model.mi_proyecto_dbt.avg_hum", "compiled": true, "compiled_code": "\n\n\nWITH base AS (\n    SELECT\n        city,\n        CAST(date AS DATE) AS date_day,\n        CAST(humidity AS INT) AS humidity\n    FROM \"airflow\".\"pro_raw_api\".\"daily_weather\"  \n)\n\nSELECT\n    city,\n    date_day AS date,\n    AVG(humidity) AS humidity\nFROM base\nGROUP BY\n    city,\n    date_day", "relation_name": "\"airflow\".\"pro_raw_api\".\"avg_hum\"", "batch_results": null}, {"status": "success", "timing": [{"name": "compile", "started_at": "2025-04-08T10:05:31.400999Z", "completed_at": "2025-04-08T10:05:31.412203Z"}, {"name": "execute", "started_at": "2025-04-08T10:05:31.413552Z", "completed_at": "2025-04-08T10:05:31.582618Z"}], "thread_id": "Thread-1", "execution_time": 0.18648290634155273, "adapter_response": {"_message": "SELECT 7775", "code": "SELECT", "rows_affected": 7775}, "message": "SELECT 7775", "failures": null, "unique_id": "model.mi_proyecto_dbt.avg_temp", "compiled": true, "compiled_code": "\n\n\nWITH base AS (\n    SELECT\n        city,\n        CAST(date AS DATE) AS date_day,\n        CAST(temperature AS FLOAT) AS temperature\n    FROM \"airflow\".\"pro_raw_api\".\"daily_weather\" \n)\n\nSELECT\n    city,\n    date_day AS date,\n    AVG(temperature) AS avg_temperature\nFROM base\nGROUP BY\n    city,\n    date_day", "relation_name": "\"airflow\".\"pro_raw_api\".\"avg_temp\"", "batch_results": null}, {"status": "success", "timing": [{"name": "compile", "started_at": "2025-04-08T10:05:31.593479Z", "completed_at": "2025-04-08T10:05:31.604988Z"}, {"name": "execute", "started_at": "2025-04-08T10:05:31.606169Z", "completed_at": "2025-04-08T10:05:31.775384Z"}], "thread_id": "Thread-1", "execution_time": 0.18563055992126465, "adapter_response": {"_message": "SELECT 20", "code": "SELECT", "rows_affected": 20}, "message": "SELECT 20", "failures": null, "unique_id": "model.mi_proyecto_dbt.max_temp_summer", "compiled": true, "compiled_code": "\n\nWITH base AS (\n    SELECT *\n    FROM \"airflow\".\"pro_raw_api\".\"daily_weather\"\n    WHERE EXTRACT(MONTH FROM CAST(date AS timestamp)) IN (6, 7, 8)\n),\nmax_temp AS (\n    SELECT \n        city,\n        EXTRACT(YEAR FROM CAST(date AS timestamp)) AS year,\n        MAX(temperature) AS max_temp\n    FROM base\n    GROUP BY city, EXTRACT(YEAR FROM CAST(date AS timestamp))\n)\n\nSELECT b.*\nFROM base b\nJOIN max_temp m \n    ON b.city = m.city \n    AND EXTRACT(YEAR FROM CAST(b.date AS timestamp)) = m.year\n    AND b.temperature = m.max_temp", "relation_name": "\"airflow\".\"pro_raw_api\".\"max_temp_summer\"", "batch_results": null}, {"status": "success", "timing": [{"name": "compile", "started_at": "2025-04-08T10:05:31.786483Z", "completed_at": "2025-04-08T10:05:31.795789Z"}, {"name": "execute", "started_at": "2025-04-08T10:05:31.797154Z", "completed_at": "2025-04-08T10:05:31.924072Z"}], "thread_id": "Thread-1", "execution_time": 0.14149141311645508, "adapter_response": {"_message": "SELECT 5", "code": "SELECT", "rows_affected": 5}, "message": "SELECT 5", "failures": null, "unique_id": "model.mi_proyecto_dbt.max_wind", "compiled": true, "compiled_code": "\n\nWITH base AS (\n    SELECT *\n    FROM \"airflow\".\"pro_raw_api\".\"daily_weather\"\n),\nmax_wind AS (\n    SELECT city, MAX(wind_kph) AS max_wind\n    FROM base\n    GROUP BY city\n)\n\nSELECT b.*\nFROM base b\nJOIN max_wind m \n    ON b.city = m.city \n    AND b.wind_kph = m.max_wind", "relation_name": "\"airflow\".\"pro_raw_api\".\"max_wind\"", "batch_results": null}, {"status": "success", "timing": [{"name": "compile", "started_at": "2025-04-08T10:05:31.936701Z", "completed_at": "2025-04-08T10:05:31.946805Z"}, {"name": "execute", "started_at": "2025-04-08T10:05:31.948318Z", "completed_at": "2025-04-08T10:05:32.067437Z"}], "thread_id": "Thread-1", "execution_time": 0.134962797164917, "adapter_response": {"_message": "SELECT 5", "code": "SELECT", "rows_affected": 5}, "message": "SELECT 5", "failures": null, "unique_id": "model.mi_proyecto_dbt.min_temp", "compiled": true, "compiled_code": "\n\nWITH base AS (\n    SELECT *\n    FROM \"airflow\".\"pro_raw_api\".\"daily_weather\"\n),\nmin_temp AS (\n    SELECT city, MIN(temperature) AS min_temp\n    FROM base\n    GROUP BY city\n)\n\nSELECT b.*\nFROM base b\nJOIN min_temp m \n    ON b.city = m.city \n    AND b.temperature = m.min_temp", "relation_name": "\"airflow\".\"pro_raw_api\".\"min_temp\"", "batch_results": null}, {"status": "success", "timing": [{"name": "compile", "started_at": "2025-04-08T10:05:32.078152Z", "completed_at": "2025-04-08T10:05:32.087234Z"}, {"name": "execute", "started_at": "2025-04-08T10:05:32.088440Z", "completed_at": "2025-04-08T10:05:32.227771Z"}], "thread_id": "Thread-1", "execution_time": 0.15283679962158203, "adapter_response": {"_message": "SELECT 2417", "code": "SELECT", "rows_affected": 2417}, "message": "SELECT 2417", "failures": null, "unique_id": "model.mi_proyecto_dbt.precip_day", "compiled": true, "compiled_code": "\n\n\nWITH base AS (\n    SELECT\n        *\n    FROM \"airflow\".\"pro_raw_api\".\"daily_weather\"  \n)\n\nSELECT\n    *\nFROM base\nWHERE precip_mm > 0", "relation_name": "\"airflow\".\"pro_raw_api\".\"precip_day\"", "batch_results": null}], "elapsed_time": 1.2921724319458008, "args": {"indirect_selection": "eager", "project_dir": "/usr/app/dbt_project", "exclude": [], "require_resource_names_without_spaces": false, "warn_error_options": {"include": [], "exclude": []}, "require_batched_execution_for_custom_microbatch_strategy": false, "require_nested_cumulative_type_params": false, "vars": {}, "use_colors_file": true, "skip_nodes_if_on_run_start_fails": false, "profiles_dir": "/usr/app/dbt_project/.dbt", "empty": false, "static_parser": true, "use_colors": true, "partial_parse": true, "state_modified_compare_more_unrendered_values": false, "send_anonymous_usage_stats": true, "introspect": true, "select": [], "log_format": "default", "source_freshness_run_project_hooks": false, "favor_state": false, "defer": false, "macro_debugging": false, "populate_cache": true, "log_level": "info", "state_modified_compare_vars": false, "log_path": "/usr/app/dbt_project/logs", "quiet": false, "cache_selected_only": false, "require_explicit_package_overrides_for_builtin_materializations": true, "version_check": true, "partial_parse_file_diff": true, "which": "run", "log_format_file": "debug", "printer_width": 80, "require_yaml_configuration_for_mf_time_spines": false, "log_file_max_bytes": 10485760, "log_level_file": "debug", "show_resource_report": false, "print": true, "invocation_command": "dbt run", "write_json": true, "strict_mode": false}}